ribodetector/__init__.py
ribodetector/config.json
ribodetector/convert_onnx.py
ribodetector/detect.py
ribodetector/detect_cpu.py
ribodetector/parse_config.py
ribodetector/base/__init__.py
ribodetector/base/base_data_loader.py
ribodetector/base/base_model.py
ribodetector/benchmarks/benchmarks.jpg
ribodetector/data/__init__.py
ribodetector/data/ribodetector_600k_variable_len70_101_epoch47.onnx
ribodetector/data/ribodetector_600k_variable_len70_101_epoch47.pth
ribodetector/data_loader/__init__.py
ribodetector/data_loader/dataset.py
ribodetector/data_loader/fastx_parser.py
ribodetector/data_loader/seq_encoder.py
ribodetector/logger/__init__.py
ribodetector/logger/logger.py
ribodetector/logger/logger_config.json
ribodetector/model/__init__.py
ribodetector/model/loss.py
ribodetector/model/metric.py
ribodetector/model/model.py
ribodetector/model/model_cpu.py
ribodetector/utils/__init__.py
ribodetector/utils/__version__.py
ribodetector/utils/pickle4reducer.py
ribodetector/utils/util.py
ribodetector-0.3.0.dist-info/LICENSE
ribodetector-0.3.0.dist-info/METADATA
ribodetector-0.3.0.dist-info/WHEEL
ribodetector-0.3.0.dist-info/entry_points.txt
ribodetector-0.3.0.dist-info/top_level.txt
ribodetector-0.3.0.dist-info/zip-safe
ribodetector-0.3.0.dist-info/RECORD
