Metadata-Version: 2.1
Name: ribodetector
Version: 0.3.0
Summary: Accurate and rapid RiboRNA sequences Detector based on deep learning.
Home-page: https://github.com/hzi-bifo/RiboDetector
Author: Z-L Deng
Author-email: dawnmsg@gmail.com
License: GPL-3 License
Classifier: Topic :: Scientific/Engineering :: Artificial Intelligence
Classifier: Topic :: Scientific/Engineering :: Bio-Informatics
Classifier: Intended Audience :: Science/Research
Classifier: Programming Language :: Python :: 3
Classifier: Operating System :: OS Independent
Requires-Python: >=3.8, <=3.10
License-File: LICENSE
Requires-Dist: pandas
Requires-Dist: tqdm
Requires-Dist: numpy
Requires-Dist: biopython
Requires-Dist: onnxruntime <=1.15.1,>=1.10.0
Requires-Dist: torch <=1.12.1,>=1.7.1
